pyflim/__init__.py
pyflim/flimds.py
pyflim/functions.py
pyflim/misc.py
pyflim/plot.py
pyflim/simulation.py
pyflim/wavelets.py
pyflim/io/__init__.py
pyflim/io/functions.py
pyflim/io/picoquant/__init__.py
pyflim/io/picoquant/pq_header.py
pyflim/io/picoquant/pq_numba.py
pyflim/tests/__init__.py
pyflim/tests/io/__init__.py
pyflim/tests/io/picoquant/__init__.py
pyflim/tests/io/picoquant/picoquant.py
pyflim-0.0.0.dist-info/LICENSE
pyflim-0.0.0.dist-info/METADATA
pyflim-0.0.0.dist-info/WHEEL
pyflim-0.0.0.dist-info/top_level.txt
pyflim-0.0.0.dist-info/RECORD
